mi4_conventional_commits_lib/__init__.py
mi4_conventional_commits_lib/validator.py
mi4_conventional_commits_lib-0.1.7.dist-info/METADATA
mi4_conventional_commits_lib-0.1.7.dist-info/WHEEL
mi4_conventional_commits_lib-0.1.7.dist-info/top_level.txt
mi4_conventional_commits_lib-0.1.7.dist-info/RECORD
